<?xml version="1.0" encoding="UTF-8"?>
<configuration>
    <!-- Development Profile: Text logging with colors -->
    <springProfile name="dev">
        <appender name="CONSOLE" class="ch.qos.logback.core.ConsoleAppender">
            <encoder>
                <pattern>%d{yyyy-MM-dd HH:mm:ss.SSS} %5p ${PID:- } --- [%15.15t] %-40.40logger{39} : %m%n</pattern>
            </encoder>
        </appender>
        <root level="INFO">
            <appender-ref ref="CONSOLE"/>
        </root>
        <logger name="com.opencode.orcagrid" level="DEBUG"/>
        <logger name="org.springframework.web" level="INFO"/>
    </springProfile>

    <!-- Production Profile: JSON logging -->
    <springProfile name="prod">
        <appender name="JSON" class="ch.qos.logback.core.ConsoleAppender">
            <encoder class="net.logstash.logback.encoder.LogstashEncoder">
                <includeMdc>true</includeMdc>
                <includeContext>true</includeContext>
            </encoder>
        </appender>
        <root level="INFO">
            <appender-ref ref="JSON"/>
        </root>
        <logger name="com.opencode.orcagrid" level="INFO"/>
        <logger name="org.springframework.web" level="WARN"/>
    </springProfile>
</configuration>
